mcp_baostock_server/baostock_api.py
mcp_baostock_server/server.py
iflow_mcp_mcp_baostock_server-0.1.0.dist-info/METADATA
iflow_mcp_mcp_baostock_server-0.1.0.dist-info/WHEEL
iflow_mcp_mcp_baostock_server-0.1.0.dist-info/entry_points.txt
iflow_mcp_mcp_baostock_server-0.1.0.dist-info/RECORD
