Metadata-Version: 2.4
Name: iflow-mcp_mcp-baostock-server
Version: 0.1.0
Summary: Add your description here
Requires-Python: >=3.10
Requires-Dist: baostock>=0.8.9
Requires-Dist: fastapi>=0.68.0
Requires-Dist: mcp[cli]>=1.6.0
Requires-Dist: pandas>=1.3.0
Requires-Dist: uvicorn>=0.15.0
